{
    "ASPIRES": {
      "Definition": "to have a great ambition or ultimate goal; desire strongly"
    },
    "ATTEMPTING": {
      "Definition": "trying to do something"
    },
    "SUSTAIN": {
      "Definition": "to keep something in operation; maintain"
    },
    "REVENUE": {
      "Definition": "the income that a company receives regularly"
    },
    "ALTHOUGH": {
      "Definition": "despite the fact that"
    },
    "NO-BRAINER": {
      "Definition": "it's an easy decision or choice to make"
    },
    "ONBOARDING": {
      "Definition": "the action or process of integrating a new member into an organization"
    },
    "FACILITATE": {
      "Definition": "to make something easier"
    },
    "APPROACH": {
      "Definition": "to come near to someone; to speak to someone"
    },
    "SCAMMER": {
      "Definition": "someone who makes money using illegal methods, especially by tricking people"
    },
    "GUIDES": {
      "Definition": "a book that gives you the most important information about a particular subject"
    },
    "RUN OUT OF": {
      "Definition": "use all of something; reach end of available amount"
    },
    "STUCK": {
      "Definition": "unable to change or get away from a situation"
    },
    "GROWTH STAGES": {
      "Definition": "a particular phase in the gradual development of something"
    },
    "ENCOURAGING": {
      "Definition": "giving someone support or confidence"
    },
    "IMPLEMENT": {
      "Definition": "to start using a plan or system"
    },
    "TRENDY": {
      "Definition": "modern and influenced by the most recent fashions or ideas"
    },
    "STAY ON TRACK": {
      "Definition": "to continue to work or make progress as planned or expected"
    },
    "JUGGLING TOO MANY BALLS": {
      "Definition": "to have a number of different activities in progress; to deal with several things at once"
    },
    "BRAND": {
      "Definition": "an identifying symbol, logo, name or sentence companies use to distinguish their product from others"
    },
    "IMPACTFUL": {
      "Definition": "having a powerful effect on a situation or person"
    },
    "EXPOSE": {
      "Definition": "to give someone an introduction to or experience of"
    },
    "THUS": {
      "Definition": "as a result or consequence of this; therefore"
    },
    "DRAIN": {
      "Definition": "to reduce or cause something to reduce"
    },
    "VITAL": {
      "Definition": "necessary for the success of something; extremely important"
    },
    "CORE AUDIENCE": {
      "Definition": "the type of people who are most likely to buy a particular product"
    },
    "IN THE LONG RUN": {
      "Definition": "at some time in the future; eventually"
    },
    "DAWNED ON ME": {
      "Definition": "to suddenly realize something"
    },
    "SOLELY": {
      "Definition": "only; not involving anything else"
    },
    "CONDENSE": {
      "Definition": "to reduce something in length"
    },
    "SLOWLY BUT SURELY": {
      "Definition": "in slow and gradual but effective way"
    },
    "BUMP YOUR HEAD": {
      "Definition": "an expression that means ‘to make mistakes'"
    },
    "TO GET THE HANG OF THINGS": {
      "Definition": "to learn the skills that are needed to do something"
    },
    "SWEET SPOT": {
      "Definition": "a particular point, area, or range where something will be most effective or beneficial"
    },
    "BREAK THE BANK": {
      "Definition": "cost more than one can afford"
    },
    "FLAT RATE": {
      "Definition": "a charge that is the same in all cases"
    },
    "HACKS": {
      "Definition": "a trick that will help you finish something faster or more effectively"
    },
    "RAMBLING": {
      "Definition": "proceeding without a specific goal or direction"
    },
    "MARKETING": {
      "Definition": "to promote the buying or selling of a product or service"
    },
    "ENVISIONED": {
      "Definition": "imagine as a future possibility; visualize"
    },
    "FORGE": {
      "Definition": "to bring into existence; create"
    },
    "GENERATE": {
      "Definition": "to cause something to exist"
    },
    "BUCKS": {
      "Definition": "slang for dollars"
    },
    "ONGOING SERVICE": {
      "Definition": "continually moving forward; remaining in existence"
    },
    "MERCHANDISE": {
      "Definition": "branded products used to promote a service"
    },
    "PORTION": {
      "Definition": "a part or share of something"
    },
    "QUESTION MARKS": {
      "Definition": "something unknown or uncertain"
    }
  }